agmem-0.1.3.dist-info/licenses/LICENSE
memvcs/__init__.py
memvcs/cli.py
memvcs/commands/__init__.py
memvcs/commands/add.py
memvcs/commands/audit.py
memvcs/commands/base.py
memvcs/commands/blame.py
memvcs/commands/branch.py
memvcs/commands/checkout.py
memvcs/commands/clean.py
memvcs/commands/clone.py
memvcs/commands/commit.py
memvcs/commands/daemon.py
memvcs/commands/decay.py
memvcs/commands/diff.py
memvcs/commands/distill.py
memvcs/commands/federated.py
memvcs/commands/fsck.py
memvcs/commands/garden.py
memvcs/commands/gc.py
memvcs/commands/graph.py
memvcs/commands/init.py
memvcs/commands/log.py
memvcs/commands/mcp.py
memvcs/commands/merge.py
memvcs/commands/pack.py
memvcs/commands/prove.py
memvcs/commands/pull.py
memvcs/commands/push.py
memvcs/commands/recall.py
memvcs/commands/reflog.py
memvcs/commands/remote.py
memvcs/commands/repair.py
memvcs/commands/reset.py
memvcs/commands/resolve.py
memvcs/commands/resurrect.py
memvcs/commands/search.py
memvcs/commands/serve.py
memvcs/commands/show.py
memvcs/commands/stash.py
memvcs/commands/status.py
memvcs/commands/tag.py
memvcs/commands/test.py
memvcs/commands/timeline.py
memvcs/commands/tree.py
memvcs/commands/verify.py
memvcs/commands/when.py
memvcs/core/__init__.py
memvcs/core/access_index.py
memvcs/core/audit.py
memvcs/core/config_loader.py
memvcs/core/consistency.py
memvcs/core/constants.py
memvcs/core/crypto_verify.py
memvcs/core/decay.py
memvcs/core/diff.py
memvcs/core/distiller.py
memvcs/core/encryption.py
memvcs/core/federated.py
memvcs/core/gardener.py
memvcs/core/hooks.py
memvcs/core/ipfs_remote.py
memvcs/core/knowledge_graph.py
memvcs/core/merge.py
memvcs/core/objects.py
memvcs/core/pack.py
memvcs/core/pii_scanner.py
memvcs/core/privacy_budget.py
memvcs/core/refs.py
memvcs/core/remote.py
memvcs/core/repository.py
memvcs/core/schema.py
memvcs/core/staging.py
memvcs/core/temporal_index.py
memvcs/core/test_runner.py
memvcs/core/trust.py
memvcs/core/vector_store.py
memvcs/core/zk_proofs.py
memvcs/core/llm/__init__.py
agmem-0.1.3.dist-info/METADATA
agmem-0.1.3.dist-info/WHEEL
agmem-0.1.3.dist-info/entry_points.txt
agmem-0.1.3.dist-info/top_level.txt
agmem-0.1.3.dist-info/RECORD
