Metadata-Version: 2.4
Name: agmem
Version: 0.1.3
Summary: Agentic Memory Version Control System - Git for AI agent memories
Home-page: https://github.com/vivek-tiwari-vt/agmem
Author: agmem Team
Author-email: agmem Team <team@agmem.dev>
License: MIT
Project-URL: Homepage, https://github.com/vivek-tiwari-vt/agmem
Project-URL: Documentation, https://github.com/vivek-tiwari-vt/agmem#readme
Project-URL: Repository, https://github.com/vivek-tiwari-vt/agmem
Project-URL: Bug Tracker, https://github.com/vivek-tiwari-vt/agmem/issues
Keywords: ai,agent,memory,version-control,git,vcs,llm,merkle,audit,encryption,differential-privacy,trust,multi-agent
Classifier: Development Status :: 3 - Alpha
Classifier: Intended Audience :: Developers
Classifier: License :: OSI Approved :: MIT License
Classifier: Operating System :: OS Independent
Classifier: Programming Language :: Python :: 3
Classifier: Programming Language :: Python :: 3.9
Classifier: Programming Language :: Python :: 3.10
Classifier: Programming Language :: Python :: 3.11
Classifier: Programming Language :: Python :: 3.12
Classifier: Topic :: Software Development :: Version Control
Classifier: Topic :: Scientific/Engineering :: Artificial Intelligence
Classifier: Topic :: Security :: Cryptography
Requires-Python: >=3.8
License-File: LICENSE
Requires-Dist: PyYAML>=6.0.0
Provides-Extra: dev
Requires-Dist: pytest>=7.0.0; extra == "dev"
Requires-Dist: pytest-cov>=4.0.0; extra == "dev"
Requires-Dist: black==24.10.0; extra == "dev"
Requires-Dist: flake8>=5.0.0; extra == "dev"
Requires-Dist: mypy>=1.0.0; extra == "dev"
Provides-Extra: llm
Requires-Dist: openai>=1.0.0; extra == "llm"
Requires-Dist: anthropic>=0.18.0; extra == "llm"
Provides-Extra: mcp
Requires-Dist: mcp>=1.0.0; extra == "mcp"
Provides-Extra: vector
Requires-Dist: sqlite-vec>=0.1.0; extra == "vector"
Requires-Dist: sentence-transformers>=2.0.0; extra == "vector"
Provides-Extra: web
Requires-Dist: fastapi>=0.100.0; extra == "web"
Requires-Dist: uvicorn>=0.22.0; extra == "web"
Provides-Extra: cloud
Requires-Dist: boto3>=1.34.0; extra == "cloud"
Requires-Dist: google-cloud-storage>=2.0.0; extra == "cloud"
Provides-Extra: gardener
Requires-Dist: scikit-learn>=1.3.0; extra == "gardener"
Requires-Dist: openai>=1.0.0; extra == "gardener"
Provides-Extra: anthropic
Requires-Dist: anthropic>=0.18.0; extra == "anthropic"
Provides-Extra: pii
Requires-Dist: presidio-analyzer>=2.2.0; extra == "pii"
Provides-Extra: daemon
Requires-Dist: watchdog>=3.0.0; extra == "daemon"
Provides-Extra: graph
Requires-Dist: networkx>=3.0; extra == "graph"
Provides-Extra: pack
Requires-Dist: tiktoken>=0.5.0; extra == "pack"
Provides-Extra: distill
Requires-Dist: openai>=1.0.0; extra == "distill"
Provides-Extra: verify
Requires-Dist: openai>=1.0.0; extra == "verify"
Provides-Extra: crypto
Requires-Dist: cryptography>=41.0.0; extra == "crypto"
Provides-Extra: ipfs
Requires-Dist: requests>=2.28.0; extra == "ipfs"
Provides-Extra: all
Requires-Dist: mcp>=1.0.0; extra == "all"
Requires-Dist: cryptography>=41.0.0; extra == "all"
Requires-Dist: sqlite-vec>=0.1.0; extra == "all"
Requires-Dist: sentence-transformers>=2.0.0; extra == "all"
Requires-Dist: fastapi>=0.100.0; extra == "all"
Requires-Dist: uvicorn>=0.22.0; extra == "all"
Requires-Dist: boto3>=1.34.0; extra == "all"
Requires-Dist: google-cloud-storage>=2.0.0; extra == "all"
Requires-Dist: scikit-learn>=1.3.0; extra == "all"
Requires-Dist: openai>=1.0.0; extra == "all"
Requires-Dist: anthropic>=0.18.0; extra == "all"
Requires-Dist: watchdog>=3.0.0; extra == "all"
Requires-Dist: networkx>=3.0; extra == "all"
Requires-Dist: tiktoken>=0.5.0; extra == "all"
Requires-Dist: presidio-analyzer>=2.2.0; extra == "all"
Requires-Dist: requests>=2.28.0; extra == "all"
Dynamic: author
Dynamic: home-page
Dynamic: license-file
Dynamic: requires-python
